{
 "number": "1276",
 "date": "2012-09-01T00:00:00",
 "accumulated": 0,
 "numbers": [
  1,
  4,
  10,
  15,
  21,
  24,
  28,
  36,
  38,
  41,
  50,
  56,
  59,
  62,
  69,
  72,
  73,
  88,
  91,
  97
 ],
 "winners": [
  {
   "name": "20 números",
   "total": 0,
   "amount": 0
  },
  {
   "name": "19 números",
   "total": 8,
   "amount": 31915.45
  },
  {
   "name": "18 números",
   "total": 129,
   "amount": 1979.25
  },
  {
   "name": "17 números",
   "total": 1150,
   "amount": 138.76
  },
  {
   "name": "16 números",
   "total": 6584,
   "amount": 24.23
  },
  {
   "name": "nenhum número",
   "total": 1,
   "amount": 127661.79
  }
 ]
}