{"number":"1317","date":"2013-01-23T00:00:00","accumulated":0,"numbers":[15,22,23,33,37,43,46,48,52,53,55,60,65,66,78,79,80,89,92,96],"winners":[{"name":"Ganhadores 20 números","total":0,"amount":0},{"name":"Ganhadores 19 números","total":9,"amount":39343.62},{"name":"Ganhadores 18 números","total":183,"amount":1934.93},{"name":"Ganhadores 17 números","total":1612,"amount":137.28},{"name":"Ganhadores 16 números","total":10042,"amount":22.03},{"name":"Ganhadores nenhum número","total":0,"amount":0}]}