{"number":"1465","date":"2014-07-02T00:00:00","accumulated":0,"numbers":[1,10,11,15,18,32,34,37,40,42,44,46,54,61,62,79,83,91,92,93],"winners":[{"name":"Ganhadores 20 números","total":1,"amount":334380.3},{"name":"Ganhadores 19 números","total":2,"amount":95537.23},{"name":"Ganhadores 18 números","total":63,"amount":3032.93},{"name":"Ganhadores 17 números","total":615,"amount":194.18},{"name":"Ganhadores 16 números","total":4073,"amount":29.32},{"name":"Ganhadores nenhum número","total":0,"amount":0}]}