{
 "number": "1521",
 "date": "2015-01-14T00:00:00",
 "accumulated": 0,
 "numbers": [
  1,
  2,
  6,
  8,
  19,
  20,
  21,
  28,
  38,
  41,
  46,
  51,
  55,
  57,
  68,
  81,
  87,
  91,
  92,
  97
 ],
 "winners": [
  {
   "name": "20 números",
   "total": 0,
   "amount": 0
  },
  {
   "name": "19 números",
   "total": 11,
   "amount": 20938.34
  },
  {
   "name": "18 números",
   "total": 114,
   "amount": 2020.37
  },
  {
   "name": "17 números",
   "total": 981,
   "amount": 146.73
  },
  {
   "name": "16 números",
   "total": 6682,
   "amount": 21.54
  },
  {
   "name": "nenhum número",
   "total": 0,
   "amount": 0
  }
 ]
}