{
 "number": "1543",
 "date": "2015-04-04T00:00:00",
 "accumulated": 0,
 "numbers": [
  10,
  12,
  13,
  15,
  16,
  17,
  21,
  22,
  27,
  39,
  40,
  61,
  67,
  68,
  72,
  75,
  85,
  88,
  92,
  97
 ],
 "winners": [
  {
   "name": "20 números",
   "total": 3,
   "amount": 0.05
  },
  {
   "name": "19 números",
   "total": 79,
   "amount": 11731899.5
  },
  {
   "name": "18 números",
   "total": 1242,
   "amount": 33192.13
  },
  {
   "name": "17 números",
   "total": 11189,
   "amount": 2111.25
  },
  {
   "name": "16 números",
   "total": 68020,
   "amount": 146.47
  },
  {
   "name": "nenhum número",
   "total": null,
   "amount": 24.09
  }
 ]
}