{"number":"1791","date":"2017-08-25T00:00:00","accumulated":0,"numbers":[0,7,9,17,21,27,29,36,40,41,42,53,62,63,68,75,77,78,83,95],"winners":[{"name":"Ganhadores 20 números","total":0,"amount":0},{"name":"Ganhadores 19 números","total":10,"amount":33650.02},{"name":"Ganhadores 18 números","total":163,"amount":1843.23},{"name":"Ganhadores 17 números","total":1420,"amount":148.1},{"name":"Ganhadores 16 números","total":8921,"amount":23.57},{"name":"Ganhadores nenhum número","total":0,"amount":0}]}