{"number":"1881","date":"2018-07-06T00:00:00","accumulated":0,"numbers":[0,2,21,22,25,27,29,45,46,55,60,64,66,70,74,79,89,93,95,96],"winners":[{"name":"Ganhadores 20 números","total":0,"amount":0},{"name":"Ganhadores 19 números","total":9,"amount":29653.94},{"name":"Ganhadores 18 números","total":106,"amount":1573.62},{"name":"Ganhadores 17 números","total":994,"amount":167.81},{"name":"Ganhadores 16 números","total":6251,"amount":26.68},{"name":"Ganhadores nenhum número","total":0,"amount":0}]}