{
 "number": "2016",
 "date": "2019-10-25T00:00:00",
 "accumulated": 0,
 "numbers": [
  2,
  11,
  19,
  25,
  28,
  30,
  37,
  38,
  45,
  56,
  58,
  61,
  74,
  77,
  82,
  85,
  86,
  88,
  99,
  100
 ],
 "winners": [
  {
   "name": "20 números",
   "total": 0,
   "amount": 0
  },
  {
   "name": "19 números",
   "total": 8,
   "amount": 0
  },
  {
   "name": "18 números",
   "total": 165,
   "amount": 31490.12
  },
  {
   "name": "17 números",
   "total": 1428,
   "amount": 1363.2
  },
  {
   "name": "16 números",
   "total": 7941,
   "amount": 110.25
  },
  {
   "name": "nenhum número",
   "total": 32916,
   "amount": 19.82
  }
 ]
}