{"number":"2244","date":"2021-12-03T00:00:00","accumulated":0,"numbers":[3,10,14,18,19,26,29,37,41,42,45,51,71,76,77,80,90,92,97,98],"winners":[{"name":"Ganhadores 20 números","total":1,"amount":12751132.2},{"name":"Ganhadores 19 números","total":9,"amount":51562.4},{"name":"Ganhadores 18 números","total":117,"amount":2478.96},{"name":"Ganhadores 17 números","total":1080,"amount":268.55},{"name":"Ganhadores 16 números","total":6951,"amount":41.72},{"name":"Ganhadores nenhum número","total":30182,"amount":9.6}]}