{
 "number": "2268",
 "date": "2022-01-28T00:00:00",
 "accumulated": 0,
 "numbers": [
  1,
  7,
  10,
  18,
  29,
  31,
  39,
  42,
  43,
  53,
  56,
  60,
  67,
  79,
  81,
  83,
  89,
  93,
  98,
  100
 ],
 "winners": [
  {
   "name": "20 números",
   "total": 1,
   "amount": 0
  },
  {
   "name": "19 números",
   "total": 5,
   "amount": 2476130.73
  },
  {
   "name": "18 números",
   "total": 57,
   "amount": 43515.19
  },
  {
   "name": "17 números",
   "total": 635,
   "amount": 2385.7
  },
  {
   "name": "16 números",
   "total": 3491,
   "amount": 214.14
  },
  {
   "name": "nenhum número",
   "total": 15034,
   "amount": 38.95
  }
 ]
}