{"number":"2305","date":"2022-04-27T00:00:00","accumulated":0,"numbers":[3,4,33,35,38,42,48,54,56,61,63,69,72,76,77,78,81,84,90,98],"winners":[{"name":"Ganhadores 20 números","total":0,"amount":0},{"name":"Ganhadores 19 números","total":18,"amount":17311.33},{"name":"Ganhadores 18 números","total":159,"amount":1749.79},{"name":"Ganhadores 17 números","total":1259,"amount":154.68},{"name":"Ganhadores 16 números","total":7018,"amount":27.75},{"name":"Ganhadores nenhum número","total":25942,"amount":7.5}]}