{
 "number": "2334",
 "date": "2022-07-04T00:00:00",
 "accumulated": 0,
 "numbers": [
  3,
  9,
  18,
  20,
  36,
  39,
  42,
  44,
  51,
  66,
  68,
  70,
  73,
  81,
  85,
  89,
  91,
  92,
  93,
  100
 ],
 "winners": [
  {
   "name": "20 números",
   "total": 0,
   "amount": 0
  },
  {
   "name": "19 números",
   "total": 4,
   "amount": 60166.79
  },
  {
   "name": "18 números",
   "total": 88,
   "amount": 1709.29
  },
  {
   "name": "17 números",
   "total": 764,
   "amount": 196.88
  },
  {
   "name": "16 números",
   "total": 4426,
   "amount": 33.98
  },
  {
   "name": "nenhum número",
   "total": 18220,
   "amount": 8.25
  }
 ]
}