{
 "number": "2379",
 "date": "2022-10-17T00:00:00",
 "accumulated": 0,
 "numbers": [
  6,
  7,
  10,
  16,
  21,
  36,
  38,
  45,
  46,
  49,
  51,
  54,
  58,
  73,
  78,
  80,
  83,
  93,
  96,
  100
 ],
 "winners": [
  {
   "name": "20 números",
   "total": 0,
   "amount": 0
  },
  {
   "name": "19 números",
   "total": 13,
   "amount": 0
  },
  {
   "name": "18 números",
   "total": 81,
   "amount": 14039.51
  },
  {
   "name": "17 números",
   "total": 490,
   "amount": 1408.29
  },
  {
   "name": "16 números",
   "total": 3108,
   "amount": 232.79
  },
  {
   "name": "nenhum número",
   "total": 12629,
   "amount": 36.7
  }
 ]
}