{
 "number": "2494",
 "date": "2023-07-14T00:00:00",
 "accumulated": 0,
 "numbers": [
  7,
  24,
  36,
  38,
  39,
  47,
  50,
  53,
  56,
  57,
  58,
  64,
  65,
  71,
  74,
  77,
  80,
  81,
  86,
  89
 ],
 "winners": [
  {
   "name": "20 números",
   "total": 0,
   "amount": 0.01
  },
  {
   "name": "19 números",
   "total": 8,
   "amount": 0
  },
  {
   "name": "18 números",
   "total": 85,
   "amount": 23194.9
  },
  {
   "name": "17 números",
   "total": 639,
   "amount": 1949.15
  },
  {
   "name": "16 números",
   "total": 3135,
   "amount": 181.49
  },
  {
   "name": "nenhum número",
   "total": 12458,
   "amount": 36.99
  }
 ]
}