{
 "number": "279",
 "date": "2003-01-04T00:00:00",
 "accumulated": 0,
 "numbers": [
  1,
  5,
  7,
  16,
  20,
  25,
  30,
  35,
  36,
  51,
  58,
  59,
  62,
  73,
  79,
  81,
  86,
  87,
  91,
  94
 ],
 "winners": [
  {
   "name": "20 números",
   "total": 2,
   "amount": 396269.42
  },
  {
   "name": "19 números",
   "total": 18,
   "amount": 29353.29
  },
  {
   "name": "18 números",
   "total": 182,
   "amount": 2903.07
  },
  {
   "name": "17 números",
   "total": 1835,
   "amount": 143.43
  },
  {
   "name": "16 números",
   "total": 12428,
   "amount": 21.18
  },
  {
   "name": "nenhum número",
   "total": 2,
   "amount": 1751064.14
  }
 ]
}