{"number":"47","date":"2000-08-19T00:00:00","accumulated":0,"numbers":[7,10,11,18,21,31,34,39,42,50,70,75,78,80,82,89,92,95,96,97],"winners":[{"name":"Ganhadores 20 números","total":0,"amount":0},{"name":"Ganhadores 19 números","total":10,"amount":59434.47},{"name":"Ganhadores 18 números","total":196,"amount":3032.37},{"name":"Ganhadores 17 números","total":2091,"amount":141.7},{"name":"Ganhadores 16 números","total":15008,"amount":19.75},{"name":"Ganhadores nenhum número","total":0,"amount":0}]}