{
 "number": "1107",
 "date": "2014-09-17T00:00:00",
 "accumulated": 0,
 "numbers": [
  1,
  2,
  4,
  8,
  9,
  10,
  11,
  12,
  14,
  16,
  18,
  19,
  20,
  21,
  24
 ],
 "winners": [
  {
   "name": "15 números",
   "total": 7,
   "amount": 273352.05
  },
  {
   "name": "14 números",
   "total": 22091,
   "amount": 1166.55
  },
  {
   "name": "13 números",
   "total": 22091,
   "amount": 15
  },
  {
   "name": "12 números",
   "total": 247818,
   "amount": 6
  },
  {
   "name": "11 números",
   "total": 1293942,
   "amount": 3
  }
 ]
}