{
 "number": "1188",
 "date": "2015-03-27T00:00:00",
 "accumulated": 0,
 "numbers": [
  1,
  2,
  4,
  5,
  6,
  8,
  10,
  12,
  13,
  14,
  18,
  20,
  22,
  23,
  24
 ],
 "winners": [
  {
   "name": "15 números",
   "total": 4,
   "amount": 370853.61
  },
  {
   "name": "14 números",
   "total": 37375,
   "amount": 360.24
  },
  {
   "name": "13 números",
   "total": 37375,
   "amount": 15
  },
  {
   "name": "12 números",
   "total": 282671,
   "amount": 6
  },
  {
   "name": "11 números",
   "total": 1281067,
   "amount": 3
  }
 ]
}