{
 "number": "1287",
 "date": "2015-11-20T00:00:00",
 "accumulated": 0,
 "numbers": [
  3,
  4,
  5,
  6,
  9,
  11,
  13,
  17,
  18,
  19,
  21,
  22,
  23,
  24,
  25
 ],
 "winners": [
  {
   "name": "15 números",
   "total": 1,
   "amount": 1435915.05
  },
  {
   "name": "14 números",
   "total": 11588,
   "amount": 1889.73
  },
  {
   "name": "13 números",
   "total": 11588,
   "amount": 20
  },
  {
   "name": "12 números",
   "total": 157399,
   "amount": 8
  },
  {
   "name": "11 números",
   "total": 860308,
   "amount": 4
  }
 ]
}