{
 "number": "1481",
 "date": "2017-03-03T00:00:00",
 "accumulated": 0,
 "numbers": [
  2,
  3,
  5,
  7,
  8,
  9,
  11,
  17,
  18,
  19,
  20,
  21,
  23,
  24,
  25
 ],
 "winners": [
  {
   "name": "15 números",
   "total": 3,
   "amount": 1167875.31
  },
  {
   "name": "14 números",
   "total": 23821,
   "amount": 1640.44
  },
  {
   "name": "13 números",
   "total": 23821,
   "amount": 20
  },
  {
   "name": "12 números",
   "total": 288152,
   "amount": 8
  },
  {
   "name": "11 números",
   "total": 1416041,
   "amount": 4
  }
 ]
}