{
 "number": "1534",
 "date": "2017-07-07T00:00:00",
 "accumulated": 0,
 "numbers": [
  1,
  4,
  5,
  8,
  9,
  10,
  11,
  12,
  13,
  14,
  16,
  17,
  19,
  21,
  24
 ],
 "winners": [
  {
   "name": "15 números",
   "total": 1,
   "amount": 2051963.67
  },
  {
   "name": "14 números",
   "total": 13908,
   "amount": 1768.55
  },
  {
   "name": "13 números",
   "total": 13908,
   "amount": 20
  },
  {
   "name": "12 números",
   "total": 186284,
   "amount": 8
  },
  {
   "name": "11 números",
   "total": 1034775,
   "amount": 4
  }
 ]
}