{
 "number": "1572",
 "date": "2017-10-13T00:00:00",
 "accumulated": 0,
 "numbers": [
  2,
  4,
  5,
  6,
  8,
  9,
  10,
  13,
  16,
  18,
  19,
  21,
  22,
  23,
  24
 ],
 "winners": [
  {
   "name": "15 números",
   "total": 1,
   "amount": 1724932.85
  },
  {
   "name": "14 números",
   "total": 13173,
   "amount": 1653.43
  },
  {
   "name": "13 números",
   "total": 13173,
   "amount": 20
  },
  {
   "name": "12 números",
   "total": 162129,
   "amount": 8
  },
  {
   "name": "11 números",
   "total": 867866,
   "amount": 4
  }
 ]
}