{
 "number": "2538",
 "date": "2022-06-03T00:00:00",
 "accumulated": 0,
 "numbers": [
  1,
  2,
  4,
  5,
  6,
  8,
  9,
  13,
  14,
  16,
  17,
  21,
  22,
  24,
  25
 ],
 "winners": [
  {
   "name": "15 números",
   "total": 1,
   "amount": 1865629.16
  },
  {
   "name": "14 números",
   "total": 9024,
   "amount": 1571.01
  },
  {
   "name": "13 números",
   "total": 9024,
   "amount": 25
  },
  {
   "name": "12 números",
   "total": 114493,
   "amount": 10
  },
  {
   "name": "11 números",
   "total": 651198,
   "amount": 5
  }
 ]
}