{
 "number": "2714",
 "date": "2023-01-14T00:00:00",
 "accumulated": 0,
 "numbers": [
  2,
  3,
  5,
  6,
  8,
  9,
  11,
  13,
  16,
  17,
  18,
  21,
  23,
  24,
  25
 ],
 "winners": [
  {
   "name": "15 números",
   "total": 2,
   "amount": 668058.79
  },
  {
   "name": "14 números",
   "total": 12071,
   "amount": 1028.84
  },
  {
   "name": "13 números",
   "total": 12071,
   "amount": 25
  },
  {
   "name": "12 números",
   "total": 136125,
   "amount": 10
  },
  {
   "name": "11 números",
   "total": 724263,
   "amount": 5
  }
 ]
}